autogen_ext_email/__init__.py
autogen_ext_email/_email_agent.py
autogen_ext_email/_email_tools.py
autogen_ext_email-0.1.1.dist-info/licenses/LICENSE
autogen_ext_email-0.1.1.dist-info/METADATA
autogen_ext_email-0.1.1.dist-info/WHEEL
autogen_ext_email-0.1.1.dist-info/top_level.txt
autogen_ext_email-0.1.1.dist-info/RECORD
