Metadata-Version: 2.4
Name: autogen-ext-email
Version: 0.1.1
Summary: A Email agent for AutoGen
Author-email: masquerlin <masquerlin@example.com>
Requires-Python: >=3.10
License-File: LICENSE
Requires-Dist: autogen-agentchat==0.4.9.3
Requires-Dist: autogen_ext[openai]
Dynamic: license-file
